bits/__init__.py
bits/quay/__init__.py
bits/quay/app.py
bits/quay/client.py
bits/quay/datastore.py
bits/quay/firestore.py
bits_quay-1.0.6.dist-info/METADATA
bits_quay-1.0.6.dist-info/WHEEL
bits_quay-1.0.6.dist-info/top_level.txt
bits_quay-1.0.6.dist-info/RECORD
