Metadata-Version: 2.1
Name: bits-quay
Version: 1.0.6
Summary: BITS Quay
Home-page: UNKNOWN
Author: Lukas Karlsson
Author-email: karlsson@broadinstitute.org
License: Apache Software License
Platform: UNKNOWN
